MANIFEST.in
README.md
requirements.txt
setup.cfg
setup.py
pyalarmdotcom/__init__.py
pyalarmdotcom/pyalarmdotcom.py
pyalarmdotcom.egg-info/PKG-INFO
pyalarmdotcom.egg-info/SOURCES.txt
pyalarmdotcom.egg-info/dependency_links.txt
pyalarmdotcom.egg-info/requires.txt
pyalarmdotcom.egg-info/top_level.txt