Metadata-Version: 1.1
Name: pyalarmdotcom
Version: 0.3.2
Summary: A simple library to interface with Alarm.com built for use with Home-Assistant
Home-page: https://github.com/Xorso/pyalarmdotcom
Author: Daren Lord
Author-email: lord.daren@gmail.com
License: BSD
Download-URL: https://github.com/Xorso/pyalarmdotcom/tarball/0.3.2
Platform: UNKNOWN
Classifier: Development Status :: 3 - Alpha
Classifier: Intended Audience :: Developers
Classifier: Programming Language :: Python :: 3
